wavpool/__init__.py
wavpool/data_generators/__init__.py
wavpool/data_generators/cifar_generator.py
wavpool/data_generators/data_generator.py
wavpool/data_generators/fashion_mnist_generator.py
wavpool/data_generators/mnist_generator.py
wavpool/models/__init__.py
wavpool/models/vanillaCNN.py
wavpool/models/vanillaMLP.py
wavpool/models/wavMLP.py
wavpool/models/wavelet_layer.py
wavpool/models/wavpool.py
wavpool/training/finetune_network.py
wavpool/training/plot_results.py
wavpool/training/train_model.py
wavpool/training/training_metrics.py
wavpool/utils/__init__.py
wavpool/utils/levels.py
wavpool/utils/voting.py
wavpool-0.1.3.dist-info/LICENSE.txt
wavpool-0.1.3.dist-info/METADATA
wavpool-0.1.3.dist-info/WHEEL
wavpool-0.1.3.dist-info/RECORD
