Metadata-Version: 2.1
Name: wavpool
Version: 0.1.3
Summary: A network block with built in spacial and scale decomposition.
Home-page: https://github.com/deepskies/DeepWavNN
License: MIT
Author: M. Voetberg
Author-email: maggiev@fnal.gov
Requires-Python: >=3.10,<4.0
Classifier: License :: OSI Approved :: MIT License
Classifier: Programming Language :: Python :: 3
Classifier: Programming Language :: Python :: 3.10
Classifier: Programming Language :: Python :: 3.11
Requires-Dist: PyWavelets (>=1.4.1,<2.0.0)
Requires-Dist: bayesian-optimization (>=1.4.2,<2.0.0)
Requires-Dist: kymatio (>=0.3.0,<0.4.0)
Requires-Dist: numpy (>=1.24.2,<2.0.0)
Requires-Dist: pandas (>=1.5.3,<2.0.0)
Requires-Dist: torch (>=2.0.1,<3.0.0)
Requires-Dist: torcheval (>=0.0.6,<0.0.7)
Requires-Dist: torchvision (>=0.15.2,<0.16.0)
Project-URL: Repository, https://github.com/deepskies/DeepWavNN
